liboxide/__init__.py
liboxide/_apps.py
liboxide/_base.py
liboxide/_errors.py
liboxide/_notification.py
liboxide/_power.py
liboxide/_screen.py
liboxide/_system.py
liboxide/_util.py
liboxide/_wifi.py
liboxide/_xdgsettings.py
liboxide-0.1.2.dist-info/LICENSE
liboxide-0.1.2.dist-info/METADATA
liboxide-0.1.2.dist-info/WHEEL
liboxide-0.1.2.dist-info/top_level.txt
liboxide-0.1.2.dist-info/RECORD
