Metadata-Version: 2.1
Name: liboxide
Version: 0.1.2
Summary: Python wrapper around the oxide command line tools.
Author-email: Nathaniel van Diepen <eeems@eeems.email>
Maintainer-email: Nathaniel van Diepen <eeems@eeems.email>
Project-URL: Homepage, https://github.com/Eeems-Org/python-liboxide
Project-URL: Repository, https://github.com/Eeems-Org/python-liboxide.git
Project-URL: Issues, https://github.com/Eeems-Org/python-liboxide/issues
Classifier: Intended Audience :: Developers
Classifier: Topic :: Software Development :: Libraries
Classifier: License :: OSI Approved :: MIT License
Classifier: Programming Language :: Python :: 3.9
Classifier: Programming Language :: Python :: 3.10
Classifier: Programming Language :: Python :: 3.11
Classifier: Programming Language :: Python :: 3.12
Requires-Python: >=3.9
License-File: LICENSE
